wannabecryptolib/__init__.py
wannabecryptolib/encryptlikeapro.py
wannabecryptolib-0.0.3.dist-info/METADATA
wannabecryptolib-0.0.3.dist-info/WHEEL
wannabecryptolib-0.0.3.dist-info/top_level.txt
wannabecryptolib-0.0.3.dist-info/RECORD
